apitax/__init__.py
apitax/api/Server.py
apitax/api/__init__.py
apitax/api/__main__.py
apitax/api/encoder.py
apitax/api/util.py
apitax/api/controllers/__init__.py
apitax/api/controllers/api_controller.py
apitax/api/controllers/apitax_controller.py
apitax/api/controllers/commandtax_controller.py
apitax/api/controllers/drivers_controller.py
apitax/api/controllers/scriptax_controller.py
apitax/api/models/__init__.py
apitax/api/models/auth_response.py
apitax/api/models/base_model_.py
apitax/api/models/command.py
apitax/api/models/error_response.py
apitax/api/models/execute.py
apitax/api/models/response.py
apitax/api/models/script.py
apitax/api/models/script_create.py
apitax/api/models/script_delete.py
apitax/api/models/script_rename.py
apitax/api/models/script_save.py
apitax/api/models/user.py
apitax/api/models/user_auth.py
apitax/api/models/user_create.py
apitax/api/models/user_delete.py
apitax/api/models/user_save.py
apitax/api/swagger/swagger.yaml
apitax/api/test/__init__.py
apitax/api/test/test_api_controller.py
apitax/api/test/test_apitax_controller.py
apitax/api/test/test_commandtax_controller.py
apitax/api/test/test_drivers_controller.py
apitax/api/test/test_scriptax_controller.py
apitax/api/utilities/Lifecycle.py
apitax/api/utilities/Mappers.py
apitax/api/utilities/Roles.py
apitax/api/utilities/__init__.py
apitax/authentication/ApitaxAuthentication.py
apitax/authentication/__init__.py
apitax/catalog/EndpointCatalog.py
apitax/catalog/__init__.py
apitax/drivers/__init__.py
apitax/drivers/builtin/Apitax.py
apitax/drivers/builtin/BasicAuth.py
apitax/drivers/builtin/__init__.py
apitax/flow/Project.py
apitax/flow/Setup.py
apitax/flow/__init__.py
apitax/tests/IntegrationTest.py
apitax/tests/__init__.py
app/Project.py
app/__init__.py
app/config.example.txt
app/users.example.json
Apitax-3.0.12.dist-info/LICENSE
Apitax-3.0.12.dist-info/METADATA
Apitax-3.0.12.dist-info/WHEEL
Apitax-3.0.12.dist-info/top_level.txt
Apitax-3.0.12.dist-info/RECORD
