Metadata-Version: 2.1
Name: Apitax
Version: 3.0.12
Summary: Brings together Commandtax, Scriptax, Standard Library, and the API to create a powerful automation framework. Please use StarterPack to quickly incorporate additional drivers, configuration, and custom code into Apitax.
Home-page: https://github.com/Apitax/Apitax
Author: Shawn Clake
Author-email: shawn.clake@gmail.com
License: UNKNOWN
Keywords: restful,api,commandtax,scriptax
Platform: UNKNOWN
Classifier: Programming Language :: Python :: 3
Classifier: License :: OSI Approved :: MIT License
Classifier: Operating System :: OS Independent
Requires-Dist: connexion (==1.1.15)
Requires-Dist: flask-jwt-extended
Requires-Dist: flask-cors
Requires-Dist: python-dateutil (==2.6.0)
Requires-Dist: typing (==3.5.2.2)
Requires-Dist: setuptools (>=21.0.0)
Requires-Dist: apitaxcore (==3.0.9)
Requires-Dist: commandtax (==0.0.8)
Requires-Dist: scriptax (==0.0.6)
Requires-Dist: scriptaxstd (==0.0.11)
Requires-Dist: apitaxdrivers (==0.0.12)
